wam2layers/__init__.py
wam2layers/cli.py
wam2layers/config.py
wam2layers/download.py
wam2layers/example_cases.py
wam2layers/analysis/__init__.py
wam2layers/analysis/checks.py
wam2layers/analysis/visualization.py
wam2layers/preprocessing/__init__.py
wam2layers/preprocessing/arco.py
wam2layers/preprocessing/cmip.py
wam2layers/preprocessing/era5.py
wam2layers/preprocessing/input_validation.py
wam2layers/preprocessing/pressure_levels.py
wam2layers/preprocessing/shared.py
wam2layers/preprocessing/tableERA5model_to_pressure.csv
wam2layers/preprocessing/utils.py
wam2layers/preprocessing/xarray_append.py
wam2layers/reference/variables.py
wam2layers/tracking/__init__.py
wam2layers/tracking/backtrack.py
wam2layers/tracking/core.py
wam2layers/tracking/forwardtrack.py
wam2layers/tracking/io.py
wam2layers/tracking/shared.py
wam2layers/utils/__init__.py
wam2layers/utils/calendar.py
wam2layers/utils/grid.py
wam2layers/utils/profiling.py
wam2layers/utils/shapefile_mask.py
wam2layers/utils/tagging_region.py
wam2layers-3.3.0.dist-info/licenses/LICENSE
wam2layers-3.3.0.dist-info/METADATA
wam2layers-3.3.0.dist-info/WHEEL
wam2layers-3.3.0.dist-info/entry_points.txt
wam2layers-3.3.0.dist-info/top_level.txt
wam2layers-3.3.0.dist-info/RECORD
