Metadata-Version: 2.4
Name: wam2layers
Version: 3.3.0
Summary: Atmospheric moisture tracking model
License: Apache 2.0
Project-URL: Documentation, https://wam2layers.readthedocs.io/en/latest
Project-URL: Source code, https://github.com/WAM2layers/WAM2layers
Keywords: atmospheric rivers,hydrological cycle,meteorology,moisture recycling,moisture tracking
Classifier: License :: OSI Approved :: Apache Software License
Classifier: Programming Language :: Python
Classifier: Development Status :: 4 - Beta
Classifier: Intended Audience :: Science/Research
Classifier: Topic :: Scientific/Engineering :: Atmospheric Science
Classifier: Topic :: Scientific/Engineering :: Hydrology
Requires-Python: <3.14,>=3.11
License-File: LICENSE
Requires-Dist: numpy
Requires-Dist: pyyaml
Requires-Dist: scipy
Requires-Dist: pandas
Requires-Dist: xarray
Requires-Dist: netcdf4
Requires-Dist: cftime
Requires-Dist: scipy
Requires-Dist: click
Requires-Dist: pydantic
Requires-Dist: dask
Requires-Dist: distributed
Requires-Dist: psutil
Requires-Dist: regionmask
Requires-Dist: matplotlib
Requires-Dist: cmocean
Requires-Dist: seaborn
Requires-Dist: threddsclient
Requires-Dist: pyshp
Requires-Dist: shapely
Provides-Extra: viz
Requires-Dist: cartopy; extra == "viz"
Provides-Extra: arco
Requires-Dist: zarr; extra == "arco"
Requires-Dist: gcsfs; extra == "arco"
Provides-Extra: dev
Requires-Dist: black; extra == "dev"
Requires-Dist: cffconvert; extra == "dev"
Requires-Dist: isort; extra == "dev"
Requires-Dist: ipdb; extra == "dev"
Requires-Dist: pytest; extra == "dev"
Requires-Dist: pre-commit; extra == "dev"
Requires-Dist: flake8; extra == "dev"
Requires-Dist: mypy; extra == "dev"
Requires-Dist: wam2layers[viz]; extra == "dev"
Provides-Extra: docs
Requires-Dist: myst-nb; extra == "docs"
Requires-Dist: sphinx_rtd_theme; extra == "docs"
Requires-Dist: sphinx; extra == "docs"
Requires-Dist: myst-nb; extra == "docs"
Provides-Extra: complete
Requires-Dist: wam2layers[arco,dev,docs,viz]; extra == "complete"
Dynamic: license-file
